regot-0.0.3.dist-info/RECORD
regot-0.0.3.dist-info/WHEEL
regot-0.0.3.dist-info/top_level.txt
regot-0.0.3.dist-info/METADATA
regot-0.0.3.dist-info/licenses/AUTHORS.md
regot-0.0.3.dist-info/licenses/LICENSE
regot/__init__.py
regot/_internal.cpython-310-darwin.so
