Metadata-Version: 2.4
Name: regot
Version: 0.0.3
Summary: Regularized Optimal Transport
Home-page: https://github.com/yixuan/regot-python
Author: ['Yixuan Qiu', 'Chenrui Wang']
Author-email: Yixuan Qiu <yixuanq@gmail.com>, Chenrui Wang <iamwangchenrui@gmail.com>
Maintainer-email: Yixuan Qiu <yixuanq@gmail.com>
License: MIT License
Project-URL: Homepage, https://github.com/yixuan/regot-python
Project-URL: Issues, https://github.com/yixuan/regot-python/issues
Requires-Python: >=3.10
License-File: LICENSE
License-File: AUTHORS.md
Requires-Dist: numpy>=1.23.0
Dynamic: author
Dynamic: home-page
Dynamic: license-file
Dynamic: requires-python
